que_media/__init__.py
que_media/_version.py
que_media/asset_management.py
que_media/basesdk.py
que_media/httpclient.py
que_media/py.typed
que_media/sdk.py
que_media/sdkconfiguration.py
que_media/utility.py
que_media/_hooks/__init__.py
que_media/_hooks/registration.py
que_media/_hooks/sdkhooks.py
que_media/_hooks/types.py
que_media/errors/__init__.py
que_media/errors/no_response_error.py
que_media/errors/problemresponse_error.py
que_media/errors/quedefaulterror.py
que_media/errors/queerror.py
que_media/errors/responsevalidationerror.py
que_media/models/__init__.py
que_media/models/assetrefdto.py
que_media/models/cawgidentitydto.py
que_media/models/cawgverifydto.py
que_media/models/getpresignedurlop.py
que_media/models/gettrustlistop.py
que_media/models/healthzresponse.py
que_media/models/limitsdto.py
que_media/models/presignedurl.py
que_media/models/presignresponse.py
que_media/models/problemresponse_error.py
que_media/models/s3.py
que_media/models/security.py
que_media/models/signassetop.py
que_media/models/signerrefdto.py
que_media/models/signrequest.py
que_media/models/signresponse.py
que_media/models/trustlistresponse.py
que_media/models/verifyassetop.py
que_media/models/verifyrequest.py
que_media/models/verifyresponse.py
que_media/types/__init__.py
que_media/types/basemodel.py
que_media/utils/__init__.py
que_media/utils/annotations.py
que_media/utils/datetimes.py
que_media/utils/enums.py
que_media/utils/eventstreaming.py
que_media/utils/forms.py
que_media/utils/headers.py
que_media/utils/logger.py
que_media/utils/metadata.py
que_media/utils/queryparams.py
que_media/utils/requestbodies.py
que_media/utils/retries.py
que_media/utils/security.py
que_media/utils/serializers.py
que_media/utils/unmarshal_json_response.py
que_media/utils/url.py
que_media/utils/values.py
que_media-0.1.0.dist-info/METADATA
que_media-0.1.0.dist-info/WHEEL
que_media-0.1.0.dist-info/top_level.txt
que_media-0.1.0.dist-info/RECORD
