Metadata-Version: 2.4
Name: que_media
Version: 0.1.0
Summary: Python Client SDK Generated by Speakeasy.
Author: Speakeasy
Project-URL: repository, https://github.com/QuePlatform/PythonSDK.git
Requires-Python: >=3.9.2
Requires-Dist: httpcore>=1.0.9
Requires-Dist: httpx>=0.28.1
Requires-Dist: pydantic>=2.11.2
